fontawesome_6/__init__.py
fontawesome_6/app_settings.py
fontawesome_6/fields.py
fontawesome_6/forms.py
fontawesome_6/icons.json
fontawesome_6/icons_semantic_ui.json
fontawesome_6/models.py
fontawesome_6/renderers.py
fontawesome_6/shims.py
fontawesome_6/utils.py
fontawesome_6/widgets.py
fontawesome_6/static/fontawesome_6/LICENSE.txt
fontawesome_6/static/fontawesome_6/css/all.min.css
fontawesome_6/static/fontawesome_6/css/django-fontawesome.css
fontawesome_6/static/fontawesome_6/js/all.min.js
fontawesome_6/static/fontawesome_6/js/django-fontawesome.js
fontawesome_6/static/fontawesome_6/webfonts/fa-brands-400.ttf
fontawesome_6/static/fontawesome_6/webfonts/fa-brands-400.woff2
fontawesome_6/static/fontawesome_6/webfonts/fa-regular-400.ttf
fontawesome_6/static/fontawesome_6/webfonts/fa-regular-400.woff2
fontawesome_6/static/fontawesome_6/webfonts/fa-solid-900.ttf
fontawesome_6/static/fontawesome_6/webfonts/fa-solid-900.woff2
fontawesome_6/static/fontawesome_6/webfonts/fa-v4compatibility.ttf
fontawesome_6/static/fontawesome_6/webfonts/fa-v4compatibility.woff2
fontawesome_6/templates/fontawesome_6/select.html
fontawesome_6/templatetags/__init__.py
fontawesome_6/templatetags/fontawesome_6.py
django_fontawesome_6-1.0.0.0.dist-info/LICENSE
django_fontawesome_6-1.0.0.0.dist-info/METADATA
django_fontawesome_6-1.0.0.0.dist-info/WHEEL
django_fontawesome_6-1.0.0.0.dist-info/top_level.txt
django_fontawesome_6-1.0.0.0.dist-info/RECORD
