Metadata-Version: 2.1
Name: django-fontawesome-6
Version: 1.0.0.0
Summary: A utility for using icons in models, forms, and templates.
Home-page: https://github.com/saschaludwig/django-fontawesome-6
Author: Sascha Ludwig
Author-email: sascha@astrastudio.de
License: BSD License
Platform: UNKNOWN
Classifier: Environment :: Web Environment
Classifier: Framework :: Django
Classifier: Intended Audience :: Developers
Classifier: License :: OSI Approved :: BSD License
Classifier: Operating System :: OS Independent
Classifier: Topic :: Utilities
